flask_request_arg/__init__.py
flask_request_arg/request_arg.py
flask_request_arg-1.0.5.dist-info/LICENSE
flask_request_arg-1.0.5.dist-info/METADATA
flask_request_arg-1.0.5.dist-info/WHEEL
flask_request_arg-1.0.5.dist-info/top_level.txt
flask_request_arg-1.0.5.dist-info/RECORD
