Metadata-Version: 2.1
Name: flask-request-arg
Version: 1.0.5
Summary: Easy way to convert Flask request form, header, JSON and parameters to route arguments.
Home-page: https://github.com/Martlark/flask-request-arg
Download-URL: https://github.com/Martlark/flask-request-arg/archive/1.0.5.tar.gz
Author: Andrew Rowe
Author-email: rowe.andrew.d@gmail.com
License: Apache Software License
Keywords: flask request arguments form json headers parameters
Classifier: Development Status :: 5 - Production/Stable
Classifier: Intended Audience :: Developers
Classifier: Topic :: Software Development :: Libraries :: Python Modules
Classifier: Framework :: Flask
Classifier: License :: OSI Approved :: Apache Software License
Classifier: Programming Language :: Python
Classifier: Programming Language :: Python :: 3
Classifier: Programming Language :: Python :: 3.7
Classifier: Programming Language :: Python :: 3.8
Classifier: Programming Language :: Python :: 3.9
Classifier: Programming Language :: Python :: 3.10
Classifier: Programming Language :: Python :: 3.11
Classifier: Operating System :: POSIX
Classifier: Operating System :: MacOS
Classifier: Operating System :: Unix
Classifier: Operating System :: Microsoft :: Windows
License-File: LICENSE
